djseong/__init__.py
djseong/namespace_a/__init__.py
djseong/namespace_a/module_a.py
djseong/namespace_bar_b/__init__.py
djseong/namespace_bar_b/module_b.py
djseong_test_bar_2-0.1.2.dist-info/METADATA
djseong_test_bar_2-0.1.2.dist-info/WHEEL
djseong_test_bar_2-0.1.2.dist-info/top_level.txt
djseong_test_bar_2-0.1.2.dist-info/RECORD
