Metadata-Version: 2.1
Name: djseong-test-bar-2
Version: 0.1.2
Summary: test bar
Author-email: djseong <feedback@gmail.com>
Classifier: Programming Language :: Python :: 3
Requires-Python: >=3.7
